cdp_patches/__init__.py
cdp_patches/input/__init__.py
cdp_patches/input/async_input.py
cdp_patches/input/browsers.py
cdp_patches/input/exceptions.py
cdp_patches/input/mouse_trajectory.py
cdp_patches/input/sync_input.py
cdp_patches/input/utils.py
cdp_patches/input/os_base/__init__.py
cdp_patches/input/os_base/linux.py
cdp_patches/input/os_base/windows.py
cdp_patches-1.1.dist-info/METADATA
cdp_patches-1.1.dist-info/WHEEL
cdp_patches-1.1.dist-info/top_level.txt
cdp_patches-1.1.dist-info/RECORD
